{
  "problem": "0056_1178_A",
  "total": 8,
  "essential_count": 0,
  "results": [
    {
      "index": 0,
      "line": 65,
      "end_line": 65,
      "text": "assert (s + [x])[..|s|] == s;",
      "ablation_result": "pass",
      "ablation_time": 1.42,
      "essential": false,
      "ablation_errors": [
        "Dafny program verifier finished with 12 verified, 0 errors"
      ]
    },
    {
      "index": 1,
      "line": 72,
      "end_line": 72,
      "text": "assert (c + [v])[..|c|] == c;",
      "ablation_result": "pass",
      "ablation_time": 1.39,
      "essential": false,
      "ablation_errors": [
        "Dafny program verifier finished with 12 verified, 0 errors"
      ]
    },
    {
      "index": 2,
      "line": 81,
      "end_line": 81,
      "text": "assert a[..j+1][..j] == a[..j];",
      "ablation_result": "error",
      "ablation_time": 1.31,
      "essential": true,
      "ablation_errors": [
        "Prover error: Model parsing error: Invalid model: invalid element name 0.0, at line 216 (  0.0)",
        "Prover error: Could not parse any models",
        "smt_analysis/results/0056_1178_A/ablation_rerun/without_02.dfy(80,0): Error: a postcondition could not be proved on this return path",
        "smt_analysis/results/0056_1178_A/ablation_rerun/without_02.dfy(78,32): Related location: this is the postcondition that could not be proved",
        "Dafny program verifier finished with 11 verified, 1 error"
      ]
    },
    {
      "index": 3,
      "line": 98,
      "end_line": 98,
      "text": "assert a[..i+1] == a[..i] + [a[i]];",
      "ablation_result": "error",
      "ablation_time": 1.68,
      "essential": true,
      "ablation_errors": [
        "Prover error: Model parsing error: Invalid model: invalid element name 0.0, at line 305 (  0.0)",
        "Prover error: Could not parse any models",
        "smt_analysis/results/0056_1178_A/ablation_rerun/without_03.dfy(96,23): Error: this invariant could not be proved to be maintained by the loop",
        "Dafny program verifier finished with 11 verified, 1 error"
      ]
    },
    {
      "index": 4,
      "line": 103,
      "end_line": 103,
      "text": "assert a[..n] == a;",
      "ablation_result": "pass",
      "ablation_time": 1.51,
      "essential": false,
      "ablation_errors": [
        "Dafny program verifier finished with 12 verified, 0 errors"
      ]
    },
    {
      "index": 5,
      "line": 122,
      "end_line": 122,
      "text": "assert forall p | 0 <= p < |coalition| :: coalition[p] <= j < j + 1;",
      "ablation_result": "pass",
      "ablation_time": 1.35,
      "essential": false,
      "ablation_errors": [
        "Dafny program verifier finished with 12 verified, 0 errors"
      ]
    },
    {
      "index": 6,
      "line": 129,
      "end_line": 129,
      "text": "assert a[..n] == a;",
      "ablation_result": "pass",
      "ablation_time": 1.77,
      "essential": false,
      "ablation_errors": [
        "Dafny program verifier finished with 12 verified, 0 errors"
      ]
    },
    {
      "index": 7,
      "line": 134,
      "end_line": 134,
      "text": "assert coalition[0] == 1;",
      "ablation_result": "pass",
      "ablation_time": 1.48,
      "essential": false,
      "ablation_errors": [
        "Dafny program verifier finished with 12 verified, 0 errors"
      ]
    }
  ]
}