{
  "problem": "0080_1281_A",
  "total_assertions": 18,
  "baseline": {
    "verified": 0,
    "errors": -1,
    "timeouts": 0,
    "time": 120.0,
    "model_crash": false
  },
  "results": [
    {
      "index": 0,
      "line": 42,
      "text": "assert s[|s| - 2..] == \"po\";",
      "cvc5_verified": 0,
      "cvc5_baseline": 0,
      "cvc5_essential": false,
      "cvc5_time": 120.0,
      "z3_essential": null
    },
    {
      "index": 1,
      "line": 43,
      "text": "assert s[|s| - 1] == 'o';",
      "cvc5_verified": 0,
      "cvc5_baseline": 0,
      "cvc5_essential": false,
      "cvc5_time": 120.0,
      "z3_essential": null
    },
    {
      "index": 2,
      "line": 46,
      "text": "assert s[|s| - 4..] == \"desu\";",
      "cvc5_verified": 0,
      "cvc5_baseline": 0,
      "cvc5_essential": false,
      "cvc5_time": 120.0,
      "z3_essential": null
    },
    {
      "index": 3,
      "line": 47,
      "text": "assert s[|s| - 1] == 'u';",
      "cvc5_verified": 0,
      "cvc5_baseline": 0,
      "cvc5_essential": false,
      "cvc5_time": 120.0,
      "z3_essential": null
    },
    {
      "index": 4,
      "line": 50,
      "text": "assert s[|s| - 4..] == \"masu\";",
      "cvc5_verified": 0,
      "cvc5_baseline": 0,
      "cvc5_essential": false,
      "cvc5_time": 120.0,
      "z3_essential": null
    },
    {
      "index": 5,
      "line": 51,
      "text": "assert s[|s| - 1] == 'u';",
      "cvc5_verified": 0,
      "cvc5_baseline": 0,
      "cvc5_essential": false,
      "cvc5_time": 120.0,
      "z3_essential": null
    },
    {
      "index": 6,
      "line": 54,
      "text": "assert s[|s| - 5..] == \"mnida\";",
      "cvc5_verified": 0,
      "cvc5_baseline": 0,
      "cvc5_essential": false,
      "cvc5_time": 120.0,
      "z3_essential": null
    },
    {
      "index": 7,
      "line": 55,
      "text": "assert s[|s| - 1] == 'a';",
      "cvc5_verified": 0,
      "cvc5_baseline": 0,
      "cvc5_essential": false,
      "cvc5_time": 120.1,
      "z3_essential": null
    },
    {
      "index": 8,
      "line": 68,
      "text": "assert ValidSentence(s);",
      "cvc5_verified": 0,
      "cvc5_baseline": 0,
      "cvc5_essential": false,
      "cvc5_time": 118.1,
      "z3_essential": false
    },
    {
      "index": 9,
      "line": 71,
      "text": "assert EndsWith(s, \"po\") || EndsWith(s, \"desu\") || EndsWith(s, \"masu\") || EndsWith(s, \"mnida\");",
      "cvc5_verified": 0,
      "cvc5_baseline": 0,
      "cvc5_essential": false,
      "cvc5_time": 333.7,
      "z3_essential": false
    },
    {
      "index": 10,
      "line": 72,
      "text": "assert |s| >= 2;",
      "cvc5_verified": 0,
      "cvc5_baseline": 0,
      "cvc5_essential": false,
      "cvc5_time": 120.0,
      "z3_essential": false
    },
    {
      "index": 11,
      "line": 78,
      "text": "assert EndsWith(s, \"po\");",
      "cvc5_verified": 0,
      "cvc5_baseline": 0,
      "cvc5_essential": false,
      "cvc5_time": 120.0,
      "z3_essential": false
    },
    {
      "index": 12,
      "line": 81,
      "text": "assert EndsWith(s, \"desu\") || EndsWith(s, \"masu\");",
      "cvc5_verified": 0,
      "cvc5_baseline": 0,
      "cvc5_essential": false,
      "cvc5_time": 120.0,
      "z3_essential": false
    },
    {
      "index": 13,
      "line": 84,
      "text": "assert EndsWith(s, \"mnida\");",
      "cvc5_verified": 0,
      "cvc5_baseline": 0,
      "cvc5_essential": false,
      "cvc5_time": 120.0,
      "z3_essential": false
    },
    {
      "index": 14,
      "line": 88,
      "text": "assert results == ClassifyAll(sentences[..i]) + [ClassifySentence(sentences[i])];",
      "cvc5_verified": 0,
      "cvc5_baseline": 0,
      "cvc5_essential": false,
      "cvc5_time": 120.0,
      "z3_essential": false
    },
    {
      "index": 15,
      "line": 89,
      "text": "assert sentences[..i+1] == sentences[..i] + [sentences[i]];",
      "cvc5_verified": 0,
      "cvc5_baseline": 0,
      "cvc5_essential": false,
      "cvc5_time": 120.0,
      "z3_essential": false
    },
    {
      "index": 16,
      "line": 90,
      "text": "assert sentences[..i+1][..|sentences[..i+1]|-1] == sentences[..i];",
      "cvc5_verified": 0,
      "cvc5_baseline": 0,
      "cvc5_essential": false,
      "cvc5_time": 120.0,
      "z3_essential": false
    },
    {
      "index": 17,
      "line": 93,
      "text": "assert sentences[..|sentences|] == sentences;",
      "cvc5_verified": 0,
      "cvc5_baseline": 0,
      "cvc5_essential": false,
      "cvc5_time": 120.0,
      "z3_essential": true
    }
  ],
  "summary": {
    "total": 18,
    "z3_essential": 1,
    "cvc5_essential": 0,
    "both": 0,
    "z3_only": 1,
    "cvc5_only": 0
  }
}