{
  "id": "1370/A",
  "title": "Maximum GCD",
  "rating": 800,
  "tags": [
    "greedy",
    "implementation",
    "math",
    "number theory"
  ],
  "description": "Let's consider all integers in the range from $$$1$$$ to $$$n$$$ (inclusive).\n\nAmong all pairs of distinct integers in this range, find the maximum possible greatest common divisor of integers in pair. Formally, find the maximum value of $$$\\mathrm{gcd}(a, b)$$$, where $$$1 \\leq a < b \\leq n$$$.\n\nThe greatest common divisor, $$$\\mathrm{gcd}(a, b)$$$, of two positive integers $$$a$$$ and $$$b$$$ is the biggest integer that is a divisor of both $$$a$$$ and $$$b$$$."
}