{
  "problem": "0033_1099_A",
  "total_assertions": 2,
  "baseline": {
    "verified": 3,
    "errors": 0,
    "timeouts": 0,
    "time": 1.7,
    "model_crash": false
  },
  "results": [
    {
      "index": 0,
      "line": 61,
      "text": "assert finalWeight == WeightAfterHeight(oldWeight, i, u1, d1, u2, d2);",
      "cvc5_verified": 3,
      "cvc5_baseline": 3,
      "cvc5_essential": false,
      "cvc5_time": 1.6,
      "z3_essential": false
    },
    {
      "index": 1,
      "line": 62,
      "text": "assert Heights(i) == [i] + Heights(i - 1);",
      "cvc5_verified": 3,
      "cvc5_baseline": 3,
      "cvc5_essential": false,
      "cvc5_time": 1.5,
      "z3_essential": false
    }
  ],
  "summary": {
    "total": 2,
    "z3_essential": 0,
    "cvc5_essential": 0,
    "both": 0,
    "z3_only": 0,
    "cvc5_only": 0
  }
}